environ/__init__.py
environ/compat.py
environ/environ.py
environ/test.py
environ/test_env.txt
django_environ_alt-0.4.6.dist-info/AUTHORS.rst
django_environ_alt-0.4.6.dist-info/LICENSE.txt
django_environ_alt-0.4.6.dist-info/METADATA
django_environ_alt-0.4.6.dist-info/WHEEL
django_environ_alt-0.4.6.dist-info/top_level.txt
django_environ_alt-0.4.6.dist-info/RECORD
