Metadata-Version: 2.1
Name: django-environ-alt
Version: 0.4.6
Summary: Django-environ allows you to utilize 12factor inspired environment variables to configure your Django application.
Home-page: https://github.com/yzdann/django-environ
Author: joke2k, yzdann
Author-email: daniele.faraglia@gmail.com, yzdannn@gmail.com
License: MIT
Keywords: django environment variables 12factor
Platform: any
Classifier: Development Status :: 3 - Alpha
Classifier: Intended Audience :: Information Technology
Classifier: Framework :: Django
Classifier: Framework :: Django :: 1.8
Classifier: Framework :: Django :: 1.9
Classifier: Framework :: Django :: 1.10
Classifier: Framework :: Django :: 1.11
Classifier: Framework :: Django :: 2.0
Classifier: Programming Language :: Python
Classifier: Programming Language :: Python :: 2
Classifier: Programming Language :: Python :: 2.7
Classifier: Programming Language :: Python :: 3
Classifier: Programming Language :: Python :: 3.4
Classifier: Programming Language :: Python :: 3.5
Classifier: Programming Language :: Python :: Implementation :: CPython
Classifier: Programming Language :: Python :: Implementation :: PyPy
Classifier: Topic :: Software Development :: Libraries :: Python Modules
Classifier: Topic :: Utilities
Classifier: License :: OSI Approved :: MIT License
Classifier: Framework :: Django
